CHANGES.txt
MANIFEST.in
README.rst
requirements.txt
setup.py
sonnet/__init__.py
sonnet/betweenness_centrality_helpers.py
sonnet/graphs.py
sonnet/nxfa2.py
sonnet/tests.py
sonnet.egg-info/PKG-INFO
sonnet.egg-info/SOURCES.txt
sonnet.egg-info/dependency_links.txt
sonnet.egg-info/requires.txt
sonnet.egg-info/top_level.txt