Metadata-Version: 1.1
Name: sonnet
Version: 0.1.6
Summary: UNKNOWN
Home-page: myurl
Author: David Michael Brown
Author-email: davidmichaelbrown1@gmail.com
License: MIT
Keywords: networkx json graph javascript D3
Platform: UNKNOWN
Classifier: Development Status :: 3 - Alpha
Classifier: Intended Audience :: Developers
Classifier: Programming Language :: Python
